README.md
setup.cfg
setup.py
src/example_package/__init__.py
src/example_package/example.py
src/smallmathop.egg-info/PKG-INFO
src/smallmathop.egg-info/SOURCES.txt
src/smallmathop.egg-info/dependency_links.txt
src/smallmathop.egg-info/top_level.txt