Metadata-Version: 2.1
Name: smallmathop
Version: 0.2
Summary: Math Operations Tool
Home-page: UNKNOWN
Author: Satya
Author-email: supersuper1075@gmail.com
License: UNKNOWN
Platform: UNKNOWN
Classifier: Programming Language :: Python :: 3
Classifier: Programming Language :: Python :: 3.6
Classifier: Programming Language :: Python :: 3.7
Classifier: Programming Language :: Python :: 3.8
Requires-Python: >=3.6
